netbox_scripthelper/__init__.py
netbox_scripthelper/events.py
netbox_scripthelper/fields.py
netbox_scripthelper/utils.py
netbox_scripthelper/api/__init__.py
netbox_scripthelper/api/serializers.py
netbox_scripthelper/api/urls.py
netbox_scripthelper/api/views.py
netbox_scripthelper-0.6.0.dist-info/licenses/LICENSE
netbox_scripthelper-0.6.0.dist-info/METADATA
netbox_scripthelper-0.6.0.dist-info/WHEEL
netbox_scripthelper-0.6.0.dist-info/top_level.txt
netbox_scripthelper-0.6.0.dist-info/RECORD
