Metadata-Version: 2.4
Name: netbox_scripthelper
Version: 0.6.0
Summary: Collections of utilities for Netbox custom scripts.
Home-page: https://github.com/k1nky/netbox-scripthelper-plugin
Author: Andrey Shalashov
Author-email: avshalashov@yandex.ru
License: Apache 2.0
Keywords: netbox-scripts custom helper plugin
License-File: LICENSE
Requires-Dist: netaddr
Dynamic: author
Dynamic: author-email
Dynamic: description-content-type
Dynamic: home-page
Dynamic: keywords
Dynamic: license
Dynamic: license-file
Dynamic: requires-dist
Dynamic: summary
